pydantic_schemaforms/__init__.py
pydantic_schemaforms/enhanced_renderer.py
pydantic_schemaforms/form_field.py
pydantic_schemaforms/form_layouts.py
pydantic_schemaforms/icon_mapping.py
pydantic_schemaforms/input_types.py
pydantic_schemaforms/layout_base.py
pydantic_schemaforms/layouts.py
pydantic_schemaforms/live_validation.py
pydantic_schemaforms/model_list.py
pydantic_schemaforms/modern_renderer.py
pydantic_schemaforms/render_form.py
pydantic_schemaforms/schema_form.py
pydantic_schemaforms/simple_material_renderer.py
pydantic_schemaforms/templates.py
pydantic_schemaforms/validation.py
pydantic_schemaforms/vendor_assets.py
pydantic_schemaforms/version_check.py
pydantic_schemaforms/assets/__init__.py
pydantic_schemaforms/assets/runtime.py
pydantic_schemaforms/assets/vendor/README.md
pydantic_schemaforms/assets/vendor/vendor_manifest.json
pydantic_schemaforms/assets/vendor/bootstrap/LICENSE
pydantic_schemaforms/assets/vendor/bootstrap/bootstrap.bundle.min.js
pydantic_schemaforms/assets/vendor/bootstrap/bootstrap.min.css
pydantic_schemaforms/assets/vendor/htmx/LICENSE
pydantic_schemaforms/assets/vendor/htmx/htmx.min.js
pydantic_schemaforms/assets/vendor/imask/LICENSE
pydantic_schemaforms/assets/vendor/imask/imask.min.js
pydantic_schemaforms/assets/vendor/materialize/LICENSE
pydantic_schemaforms/assets/vendor/materialize/materialize.min.css
pydantic_schemaforms/assets/vendor/materialize/materialize.min.js
pydantic_schemaforms/inputs/__init__.py
pydantic_schemaforms/inputs/base.py
pydantic_schemaforms/inputs/datetime_inputs.py
pydantic_schemaforms/inputs/numeric_inputs.py
pydantic_schemaforms/inputs/registry.py
pydantic_schemaforms/inputs/selection_inputs.py
pydantic_schemaforms/inputs/specialized_inputs.py
pydantic_schemaforms/inputs/text_inputs.py
pydantic_schemaforms/integration/__init__.py
pydantic_schemaforms/integration/adapters.py
pydantic_schemaforms/integration/async_support.py
pydantic_schemaforms/integration/builder.py
pydantic_schemaforms-26.1.4b0.dist-info/METADATA
pydantic_schemaforms-26.1.4b0.dist-info/WHEEL
pydantic_schemaforms-26.1.4b0.dist-info/licenses/LICENSE
pydantic_schemaforms-26.1.4b0.dist-info/RECORD
