Metadata-Version: 2.4
Name: pydantic-schemaforms
Version: 26.1.4b0
Summary: Server-rendered form components and layout helpers for Pydantic models
Project-URL: Homepage, https://github.com/devsetgo/pydantic-schemaforms
Project-URL: Documentation, https://devsetgo.github.io/pydantic-schemaforms/
Project-URL: Repository, https://github.com/devsetgo/pydantic-schemaforms
Author: Mike Ryan
Maintainer: Mike Ryan
License: MIT License
License-File: LICENSE
Keywords: forms,htmx,pydantic,schema,schemaforms,ui
Classifier: Development Status :: 4 - Beta
Classifier: Framework :: FastAPI
Classifier: Framework :: Flask
Classifier: License :: OSI Approved :: MIT License
Classifier: Operating System :: MacOS :: MacOS X
Classifier: Operating System :: Microsoft :: Windows
Classifier: Operating System :: POSIX :: Linux
Classifier: Programming Language :: Python
Classifier: Programming Language :: Python :: 3
Classifier: Programming Language :: Python :: 3 :: Only
Classifier: Programming Language :: Python :: 3.14
Classifier: Topic :: Internet :: WWW/HTTP :: Dynamic Content
Requires-Python: >=3.14
Requires-Dist: pydantic-extra-types[all]>=2.10.6
Requires-Dist: pydantic>=2.7
Provides-Extra: dev
Requires-Dist: fastapi[all]==0.121.2; extra == 'dev'
Requires-Dist: flask==3.1.2; extra == 'dev'
Requires-Dist: pytest-asyncio==1.3.0; extra == 'dev'
Requires-Dist: pytest-cov==7.0.0; extra == 'dev'
Requires-Dist: pytest==9.0.1; extra == 'dev'
Provides-Extra: fastapi
Requires-Dist: fastapi>=0.110; extra == 'fastapi'
Requires-Dist: uvicorn>=0.30; extra == 'fastapi'
Provides-Extra: flask
Requires-Dist: flask>=3.0; extra == 'flask'
